pystockwatch/__init__.py
pystockwatch/pystockwatch.py
pystockwatch-0.3.4.dist-info/LICENSE
pystockwatch-0.3.4.dist-info/WHEEL
pystockwatch-0.3.4.dist-info/METADATA
pystockwatch-0.3.4.dist-info/RECORD
