Metadata-Version: 2.1
Name: pystockwatch
Version: 0.3.4
Summary: A package which calculates and visualizes the profitability and the volume change of stocks 
Home-page: https://github.com/UBC-MDS/pystockwatch
License: MIT
Author: Affrin Sultana, Helin Wang, Pavel Levchenko, Shi Yan Wang
Requires-Python: >=3.9,<4.0
Classifier: License :: OSI Approved :: MIT License
Classifier: Programming Language :: Python :: 3
Classifier: Programming Language :: Python :: 3.10
Classifier: Programming Language :: Python :: 3.9
Requires-Dist: altair (>=4.2.0,<5.0.0)
Requires-Dist: altair-viewer (>=0.4.0,<0.5.0)
Requires-Dist: pandas-datareader (>=0.10.0,<0.11.0)
Requires-Dist: plotly (>=5.5.0,<6.0.0)
Requires-Dist: yfinance (>=0.1.69,<0.2.0)
Project-URL: Documentation, https://pystockwatch.readthedocs.io
Project-URL: Repository, https://github.com/UBC-MDS/pystockwatch
